{
  "annotations": {
    "list": [
      {
        "builtIn": 1,
        "datasource": {
          "type": "grafana",
          "uid": "-- Grafana --"
        },
        "enable": true,
        "hide": true,
        "iconColor": "rgba(0, 211, 255, 1)",
        "name": "Annotations & Alerts",
        "target": {
          "limit": 100,
          "matchAny": false,
          "tags": [],
          "type": "dashboard"
        },
        "type": "dashboard"
      }
    ]
  },
  "description": "",
  "editable": true,
  "fiscalYearStartMonth": 0,
  "graphTooltip": 0,
  "id": 1,
  "links": [],
  "liveNow": true,
  "panels": [
    {
      "collapsed": false,
      "gridPos": {
        "h": 1,
        "w": 24,
        "x": 0,
        "y": 0
      },
      "id": 18,
      "panels": [],
      "title": "Allgemein",
      "type": "row"
    },
    {
      "datasource": {
        "type": "influxdb",
        "uid": "5EpK1WUVk"
      },
      "description": "",
      "fieldConfig": {
        "defaults": {
          "color": {
            "mode": "continuous-GrYlRd"
          },
          "decimals": 3,
          "mappings": [],
          "max": 5000,
          "min": 0,
          "thresholds": {
            "mode": "percentage",
            "steps": [
              {
                "color": "green",
                "value": null
              },
              {
                "color": "red",
                "value": 80
              }
            ]
          },
          "unit": "watt"
        },
        "overrides": []
      },
      "gridPos": {
        "h": 8,
        "w": 5,
        "x": 0,
        "y": 1
      },
      "id": 2,
      "options": {
        "orientation": "auto",
        "reduceOptions": {
          "calcs": [
            "lastNotNull"
          ],
          "fields": "",
          "values": false
        },
        "showThresholdLabels": false,
        "showThresholdMarkers": true
      },
      "pluginVersion": "9.4.7",
      "targets": [
        {
          "datasource": {
            "type": "influxdb",
            "uid": "5EpK1WUVk"
          },
          "groupBy": [
            {
              "params": [
                "$__interval"
              ],
              "type": "time"
            },
            {
              "params": [
                "null"
              ],
              "type": "fill"
            }
          ],
          "measurement": "Momentanleistung",
          "orderByTime": "ASC",
          "policy": "default",
          "refId": "A",
          "resultFormat": "time_series",
          "select": [
            [
              {
                "params": [
                  "Gesamt"
                ],
                "type": "field"
              },
              {
                "params": [],
                "type": "last"
              }
            ]
          ],
          "tags": []
        }
      ],
      "title": "Aktueller Verbrauch",
      "transformations": [],
      "type": "gauge"
    },
    {
      "datasource": {
        "type": "influxdb",
        "uid": "5EpK1WUVk"
      },
      "fieldConfig": {
        "defaults": {
          "color": {
            "mode": "palette-classic"
          },
          "custom": {
            "axisCenteredZero": false,
            "axisColorMode": "text",
            "axisLabel": "Leistung",
            "axisPlacement": "auto",
            "barAlignment": 0,
            "drawStyle": "line",
            "fillOpacity": 0,
            "gradientMode": "none",
            "hideFrom": {
              "legend": false,
              "tooltip": false,
              "viz": false
            },
            "lineInterpolation": "linear",
            "lineWidth": 1,
            "pointSize": 5,
            "scaleDistribution": {
              "type": "linear"
            },
            "showPoints": "auto",
            "spanNulls": false,
            "stacking": {
              "group": "A",
              "mode": "none"
            },
            "thresholdsStyle": {
              "mode": "off"
            }
          },
          "displayName": "Leistung",
          "mappings": [],
          "max": 5000,
          "min": -5000,
          "thresholds": {
            "mode": "absolute",
            "steps": [
              {
                "color": "green",
                "value": null
              },
              {
                "color": "red",
                "value": 80
              }
            ]
          },
          "unit": "watt"
        },
        "overrides": []
      },
      "gridPos": {
        "h": 8,
        "w": 19,
        "x": 5,
        "y": 1
      },
      "id": 4,
      "options": {
        "legend": {
          "calcs": [],
          "displayMode": "list",
          "placement": "bottom",
          "showLegend": true
        },
        "tooltip": {
          "mode": "single",
          "sort": "none"
        }
      },
      "targets": [
        {
          "datasource": {
            "type": "influxdb",
            "uid": "5EpK1WUVk"
          },
          "groupBy": [
            {
              "params": [
                "10s"
              ],
              "type": "time"
            },
            {
              "params": [
                "linear"
              ],
              "type": "fill"
            }
          ],
          "measurement": "Momentanleistung",
          "orderByTime": "ASC",
          "policy": "default",
          "refId": "A",
          "resultFormat": "time_series",
          "select": [
            [
              {
                "params": [
                  "Gesamt"
                ],
                "type": "field"
              },
              {
                "params": [],
                "type": "mean"
              }
            ]
          ],
          "tags": []
        }
      ],
      "title": "Leistungsverlauf",
      "type": "timeseries"
    },
    {
      "datasource": {
        "type": "influxdb",
        "uid": "5EpK1WUVk"
      },
      "fieldConfig": {
        "defaults": {
          "color": {
            "mode": "thresholds"
          },
          "custom": {
            "align": "auto",
            "cellOptions": {
              "type": "auto"
            },
            "inspect": false
          },
          "mappings": [],
          "thresholds": {
            "mode": "absolute",
            "steps": [
              {
                "color": "green",
                "value": null
              },
              {
                "color": "red",
                "value": 80
              }
            ]
          }
        },
        "overrides": [
          {
            "matcher": {
              "id": "byName",
              "options": "Time"
            },
            "properties": [
              {
                "id": "unit",
                "value": "time:DD.MM"
              },
              {
                "id": "custom.width",
                "value": 70
              },
              {
                "id": "displayName",
                "value": "Tag"
              }
            ]
          },
          {
            "matcher": {
              "id": "byName",
              "options": "EVNZaehler.difference"
            },
            "properties": [
              {
                "id": "displayName",
                "value": "Energie"
              },
              {
                "id": "unit",
                "value": "kwatth"
              },
              {
                "id": "custom.cellOptions",
                "value": {
                  "mode": "gradient",
                  "type": "gauge"
                }
              },
              {
                "id": "color",
                "value": {
                  "mode": "continuous-GrYlRd"
                }
              },
              {
                "id": "min",
                "value": 0
              },
              {
                "id": "max",
                "value": 30
              }
            ]
          }
        ]
      },
      "gridPos": {
        "h": 11,
        "w": 12,
        "x": 0,
        "y": 9
      },
      "id": 6,
      "options": {
        "footer": {
          "countRows": false,
          "fields": "",
          "reducer": [
            "sum"
          ],
          "show": true
        },
        "showHeader": true
      },
      "pluginVersion": "9.4.7",
      "targets": [
        {
          "datasource": {
            "type": "influxdb",
            "uid": "5EpK1WUVk"
          },
          "groupBy": [
            {
              "params": [
                "1d"
              ],
              "type": "time"
            },
            {
              "params": [
                "null"
              ],
              "type": "fill"
            }
          ],
          "measurement": "Wirkenergie",
          "orderByTime": "ASC",
          "policy": "default",
          "refId": "A",
          "resultFormat": "time_series",
          "select": [
            [
              {
                "params": [
                  "Bezug"
                ],
                "type": "field"
              },
              {
                "params": [],
                "type": "last"
              },
              {
                "params": [],
                "type": "difference"
              }
            ]
          ],
          "tags": []
        }
      ],
      "timeFrom": "7d",
      "title": "Leistung Bezug pro Tag",
      "transformations": [
        {
          "id": "sortBy",
          "options": {
            "fields": {},
            "sort": [
              {
                "desc": true,
                "field": "Time"
              }
            ]
          }
        }
      ],
      "type": "table"
    },
    {
      "datasource": {
        "type": "influxdb",
        "uid": "5EpK1WUVk"
      },
      "fieldConfig": {
        "defaults": {
          "color": {
            "mode": "thresholds"
          },
          "custom": {
            "align": "auto",
            "cellOptions": {
              "type": "auto"
            },
            "inspect": false
          },
          "mappings": [],
          "thresholds": {
            "mode": "absolute",
            "steps": [
              {
                "color": "green",
                "value": null
              },
              {
                "color": "red",
                "value": 80
              }
            ]
          }
        },
        "overrides": [
          {
            "matcher": {
              "id": "byName",
              "options": "Time"
            },
            "properties": [
              {
                "id": "unit",
                "value": "time:DD.MM"
              },
              {
                "id": "custom.width",
                "value": 70
              },
              {
                "id": "displayName",
                "value": "Tag"
              }
            ]
          },
          {
            "matcher": {
              "id": "byName",
              "options": "EVNZaehler.difference"
            },
            "properties": [
              {
                "id": "displayName",
                "value": "Energie"
              },
              {
                "id": "unit",
                "value": "kwatth"
              },
              {
                "id": "custom.cellOptions",
                "value": {
                  "mode": "gradient",
                  "type": "gauge"
                }
              },
              {
                "id": "color",
                "value": {
                  "mode": "continuous-GrYlRd"
                }
              },
              {
                "id": "min",
                "value": 0
              },
              {
                "id": "max",
                "value": 30
              }
            ]
          },
          {
            "matcher": {
              "id": "byName",
              "options": "Vergütung"
            },
            "properties": [
              {
                "id": "custom.width",
                "value": 150
              },
              {
                "id": "unit",
                "value": "currencyEUR"
              }
            ]
          }
        ]
      },
      "gridPos": {
        "h": 11,
        "w": 12,
        "x": 12,
        "y": 9
      },
      "id": 7,
      "options": {
        "footer": {
          "countRows": false,
          "fields": "",
          "reducer": [
            "sum"
          ],
          "show": true
        },
        "showHeader": true
      },
      "pluginVersion": "9.4.7",
      "targets": [
        {
          "datasource": {
            "type": "influxdb",
            "uid": "5EpK1WUVk"
          },
          "groupBy": [
            {
              "params": [
                "1d"
              ],
              "type": "time"
            },
            {
              "params": [
                "null"
              ],
              "type": "fill"
            }
          ],
          "measurement": "Wirkenergie",
          "orderByTime": "ASC",
          "policy": "default",
          "refId": "A",
          "resultFormat": "time_series",
          "select": [
            [
              {
                "params": [
                  "Lieferung"
                ],
                "type": "field"
              },
              {
                "params": [],
                "type": "last"
              },
              {
                "params": [],
                "type": "difference"
              }
            ]
          ],
          "tags": []
        }
      ],
      "timeFrom": "7d",
      "title": "Leistung Lieferung pro Tag",
      "transformations": [
        {
          "id": "sortBy",
          "options": {
            "fields": {},
            "sort": [
              {
                "desc": true,
                "field": "Time"
              }
            ]
          }
        },
        {
          "id": "calculateField",
          "options": {
            "alias": "Vergütung",
            "binary": {
              "left": "EVNZaehler.difference",
              "operator": "*",
              "reducer": "sum",
              "right": "0.30"
            },
            "mode": "binary",
            "reduce": {
              "reducer": "sum"
            }
          }
        }
      ],
      "type": "table"
    }
  ],
  "refresh": "5s",
  "revision": 1,
  "schemaVersion": 38,
  "style": "dark",
  "tags": [],
  "templating": {
    "list": []
  },
  "time": {
    "from": "now-30m",
    "to": "now"
  },
  "timepicker": {},
  "timezone": "",
  "title": "Smart Meter",
  "uid": "GW05tggRk",
  "version": 3,
  "weekStart": "monday"
}